Verilog/GpioEmu.v
module gpioemu (
    input wire clk,
    input wire reset,
    input wire [23:0] A1,
    input wire [23:0] A2,
    output wire [31:0] W,
    output wire [23:0] L,
    output wire [1:0] B,
    output wire valid,
	output wire  ready,
    output wire [15:0] gpio
);

    reg [48:0] result;
    reg [23:0] wA2;
    reg [23:0] wA1;
    reg [15:0] operation_count;
    reg [3:0] state;
    reg [23:0] ones_count;
    reg [23:0] tmp_ones_count;
	

    localparam IDLE = 0,
              MULT = 1,
              COUNT_ONES = 2,
              DONE = 3;

    always @(posedge clk or posedge reset) begin
        if (reset) begin
            state <= IDLE;
            result <= 0;
            ones_count <= 0;
            tmp_ones_count <= 0;
            operation_count <= 0;
        end else begin
            case (state)
                IDLE: begin
                    result <= 0;
                    wA2 <= A2;
                    wA1 <= A1;
                    tmp_ones_count <= 0;
                    if (ready) begin
                        state <= MULT;
                    end
                end
   MULT: begin
    for (integer i = 0; i < 24; i = i + 1) begin
        if (wA2[i]) begin
            result <= result + ({24'b0,wA1} << i);
        end
		
    end
    state <= COUNT_ONES;
end 
                COUNT_ONES: begin
                    for (integer i = 0; i < 32; i++) begin
                       if (result[i] == 1) begin
						tmp_ones_count = tmp_ones_count + 1;
						end
                    end
                    ones_count <= tmp_ones_count;
                    state <= DONE;
                end
                DONE: begin
                    operation_count <= operation_count + 1;
                    if (ready) begin
                        state <= IDLE;
                    end
                end
            endcase
        end
    end

    assign W = result[31:0];
    assign L = ones_count;
    assign ready = (state == IDLE || state == DONE);
    assign valid = (result[48:32] == 0);
	assign B = {ready,valid};
    assign gpio = operation_count[15:0];

endmodule

Verilog/GpioEmu_tb.v
`timescale 1ns / 1ps

module gpioemu_tb();

    reg clk;
    reg reset;
    reg [23:0] A1;
    reg [23:0] A2;
    wire [31:0] W;
    wire [23:0] L;
	wire ready;
    wire [1:0] B;
    wire valid;
    wire [15:0] gpio;

    gpioemu gpioemu_inst (
        .clk(clk),
        .reset(reset),
        .A1(A1),
        .A2(A2),
        .W(W),
        .L(L),
        .B(B),
        .valid(valid),
		.ready,
        .gpio(gpio)
    );

    always begin
        #5 clk = ~clk;
    end

    initial begin
	$dumpfile("GpioEmu.vcd");
    $dumpvars(0, gpioemu_tb);
        clk = 0;
        reset = 1;
        A1 = 0;
        A2 = 0;
        #10 reset = 0;

        @(posedge clk) begin
            A1 = 24'h123456;
            A2 = 24'h789abc;
        end

        repeat (60) @(posedge clk);

        @(posedge clk) begin
            A1 = 24'h1;
            A2 = 24'h2;
        end

        repeat (60) @(posedge clk);

        @(posedge clk) begin
            A1 = 24'h3;
            A2 = 24'h4;
        end

        repeat (60) @(posedge clk);

        $finish;
    end

    initial begin
        $monitor("%d: A1 = %h, A2 = %h, W = %h, L = %h, ready = %b, valid = %b, B = %b, gpio = %h",
                 $time, A1, A2, W, L,ready,valid,B, gpio);
    end

endmodule

Verilog/GpioEmu.vcd
$date
	Thu Apr 27 23:32:23 2023
$end
$version
	Icarus Verilog
$end
$timescale
	1ps
$end
$scope module gpioemu_tb $end
$var wire 1 ! valid $end
$var wire 1 " ready $end
$var wire 16 # gpio [15:0] $end
$var wire 32 $ W [31:0] $end
$var wire 24 % L [23:0] $end
$var wire 2 & B [1:0] $end
$var reg 24 ' A1 [23:0] $end
$var reg 24 ( A2 [23:0] $end
$var reg 1 ) clk $end
$var reg 1 * reset $end
$scope module gpioemu_inst $end
$var wire 24 + A1 [23:0] $end
$var wire 24 , A2 [23:0] $end
$var wire 24 - L [23:0] $end
$var wire 1 ) clk $end
$var wire 16 . gpio [15:0] $end
$var wire 1 " ready $end
$var wire 1 * reset $end
$var wire 1 ! valid $end
$var wire 32 / W [31:0] $end
$var wire 2 0 B [1:0] $end
$var parameter 32 1 COUNT_ONES $end
$var parameter 32 2 DONE $end
$var parameter 32 3 IDLE $end
$var parameter 32 4 MULT $end
$var reg 24 5 ones_count [23:0] $end
$var reg 16 6 operation_count [15:0] $end
$var reg 49 7 result [48:0] $end
$var reg 4 8 state [3:0] $end
$var reg 24 9 tmp_ones_count [23:0] $end
$var reg 24 : wA1 [23:0] $end
$var reg 24 ; wA2 [23:0] $end
$scope begin $ivl_for_loop0 $end
$var integer 32 < i [31:0] $end
$upscope $end
$scope begin $ivl_for_loop1 $end
$var integer 32 = i [31:0] $end
$upscope $end
$upscope $end
$upscope $end
$enddefinitions $end
$comment Show the parameter values. $end
$dumpall
b1 4
b0 3
b11 2
b10 1
$end
#0
$dumpvars
bx =
bx <
bx ;
bx :
b0 9
b0 8
b0 7
b0 6
b0 5
b11 0
b0 /
b0 .
b0 -
b0 ,
b0 +
1*
0)
b0 (
b0 '
b11 &
b0 %
b0 $
b0 #
1"
1!
$end
#5000
1)
#10000
0)
0*
#15000
b1 &
b1 0
0"
b1 8
b100100011010001010110 :
b11110001001101010111100 ;
b11110001001101010111100 (
b11110001001101010111100 ,
b100100011010001010110 '
b100100011010001010110 +
1)
#20000
0)
#25000
b0 &
b0 0
0!
b10101100000000000000000000000 $
b10101100000000000000000000000 /
b10 8
b1001000110100010101100000000000000000000000 7
b11000 <
1)
#30000
0)
#35000
b10 &
b10 0
1"
b11 8
b100 %
b100 -
b100 5
b100 9
b100000 =
1)
#40000
0)
#45000
b0 8
b1 #
b1 .
b1 6
1)
#50000
0)
#55000
0"
b0 $
b0 /
b1 &
b1 0
1!
b1 8
b0 9
b0 7
1)
#60000
0)
#65000
b0 &
b0 0
0!
b10101100000000000000000000000 $
b10101100000000000000000000000 /
b10 8
b1001000110100010101100000000000000000000000 7
b11000 <
1)
#70000
0)
#75000
b10 &
b10 0
1"
b11 8
b100 9
b100000 =
1)
#80000
0)
#85000
b0 8
b10 #
b10 .
b10 6
1)
#90000
0)
#95000
0"
b0 $
b0 /
b1 &
b1 0
1!
b1 8
b0 9
b0 7
1)
#100000
0)
#105000
b0 &
b0 0
0!
b10101100000000000000000000000 $
b10101100000000000000000000000 /
b10 8
b1001000110100010101100000000000000000000000 7
b11000 <
1)
#110000
0)
#115000
b10 &
b10 0
1"
b11 8
b100 9
b100000 =
1)
#120000
0)
#125000
b0 8
b11 #
b11 .
b11 6
1)
#130000
0)
#135000
0"
b0 $
b0 /
b1 &
b1 0
1!
b1 8
b0 9
b0 7
1)
#140000
0)
#145000
b0 &
b0 0
0!
b10101100000000000000000000000 $
b10101100000000000000000000000 /
b10 8
b1001000110100010101100000000000000000000000 7
b11000 <
1)
#150000
0)
#155000
b10 &
b10 0
1"
b11 8
b100 9
b100000 =
1)
#160000
0)
#165000
b0 8
b100 #
b100 .
b100 6
1)
#170000
0)
#175000
0"
b0 $
b0 /
b1 &
b1 0
1!
b1 8
b0 9
b0 7
1)
#180000
0)
#185000
b0 &
b0 0
0!
b10101100000000000000000000000 $
b10101100000000000000000000000 /
b10 8
b1001000110100010101100000000000000000000000 7
b11000 <
1)
#190000
0)
#195000
b10 &
b10 0
1"
b11 8
b100 9
b100000 =
1)
#200000
0)
#205000
b0 8
b101 #
b101 .
b101 6
1)
#210000
0)
#215000
0"
b0 $
b0 /
b1 &
b1 0
1!
b1 8
b0 9
b0 7
1)
#220000
0)
#225000
b0 &
b0 0
0!
b10101100000000000000000000000 $
b10101100000000000000000000000 /
b10 8
b1001000110100010101100000000000000000000000 7
b11000 <
1)
#230000
0)
#235000
b10 &
b10 0
1"
b11 8
b100 9
b100000 =
1)
#240000
0)
#245000
b0 8
b110 #
b110 .
b110 6
1)
#250000
0)
#255000
0"
b0 $
b0 /
b1 &
b1 0
1!
b1 8
b0 9
b0 7
1)
#260000
0)
#265000
b0 &
b0 0
0!
b10101100000000000000000000000 $
b10101100000000000000000000000 /
b10 8
b1001000110100010101100000000000000000000000 7
b11000 <
1)
#270000
0)
#275000
b10 &
b10 0
1"
b11 8
b100 9
b100000 =
1)
#280000
0)
#285000
b0 8
b111 #
b111 .
b111 6
1)
#290000
0)
#295000
0"
b0 $
b0 /
b1 &
b1 0
1!
b1 8
b0 9
b0 7
1)
#300000
0)
#305000
b0 &
b0 0
0!
b10101100000000000000000000000 $
b10101100000000000000000000000 /
b10 8
b1001000110100010101100000000000000000000000 7
b11000 <
1)
#310000
0)
#315000
b10 &
b10 0
1"
b11 8
b100 9
b100000 =
1)
#320000
0)
#325000
b0 8
b1000 #
b1000 .
b1000 6
1)
#330000
0)
#335000
0"
b0 $
b0 /
b1 &
b1 0
1!
b1 8
b0 9
b0 7
1)
#340000
0)
#345000
b0 &
b0 0
0!
b10101100000000000000000000000 $
b10101100000000000000000000000 /
b10 8
b1001000110100010101100000000000000000000000 7
b11000 <
1)
#350000
0)
#355000
b10 &
b10 0
1"
b11 8
b100 9
b100000 =
1)
#360000
0)
#365000
b0 8
b1001 #
b1001 .
b1001 6
1)
#370000
0)
#375000
0"
b0 $
b0 /
b1 &
b1 0
1!
b1 8
b0 9
b0 7
1)
#380000
0)
#385000
b0 &
b0 0
0!
b10101100000000000000000000000 $
b10101100000000000000000000000 /
b10 8
b1001000110100010101100000000000000000000000 7
b11000 <
1)
#390000
0)
#395000
b10 &
b10 0
1"
b11 8
b100 9
b100000 =
1)
#400000
0)
#405000
b0 8
b1010 #
b1010 .
b1010 6
1)
#410000
0)
#415000
0"
b0 $
b0 /
b1 &
b1 0
1!
b1 8
b0 9
b0 7
1)
#420000
0)
#425000
b0 &
b0 0
0!
b10101100000000000000000000000 $
b10101100000000000000000000000 /
b10 8
b1001000110100010101100000000000000000000000 7
b11000 <
1)
#430000
0)
#435000
b10 &
b10 0
1"
b11 8
b100 9
b100000 =
1)
#440000
0)
#445000
b0 8
b1011 #
b1011 .
b1011 6
1)
#450000
0)
#455000
0"
b0 $
b0 /
b1 &
b1 0
1!
b1 8
b0 9
b0 7
1)
#460000
0)
#465000
b0 &
b0 0
0!
b10101100000000000000000000000 $
b10101100000000000000000000000 /
b10 8
b1001000110100010101100000000000000000000000 7
b11000 <
1)
#470000
0)
#475000
b10 &
b10 0
1"
b11 8
b100 9
b100000 =
1)
#480000
0)
#485000
b0 8
b1100 #
b1100 .
b1100 6
1)
#490000
0)
#495000
0"
b0 $
b0 /
b1 &
b1 0
1!
b1 8
b0 9
b0 7
1)
#500000
0)
#505000
b0 &
b0 0
0!
b10101100000000000000000000000 $
b10101100000000000000000000000 /
b10 8
b1001000110100010101100000000000000000000000 7
b11000 <
1)
#510000
0)
#515000
b10 &
b10 0
1"
b11 8
b100 9
b100000 =
1)
#520000
0)
#525000
b0 8
b1101 #
b1101 .
b1101 6
1)
#530000
0)
#535000
0"
b0 $
b0 /
b1 &
b1 0
1!
b1 8
b0 9
b0 7
1)
#540000
0)
#545000
b0 &
b0 0
0!
b10101100000000000000000000000 $
b10101100000000000000000000000 /
b10 8
b1001000110100010101100000000000000000000000 7
b11000 <
1)
#550000
0)
#555000
b10 &
b10 0
1"
b11 8
b100 9
b100000 =
1)
#560000
0)
#565000
b0 8
b1110 #
b1110 .
b1110 6
1)
#570000
0)
#575000
0"
b0 $
b0 /
b1 &
b1 0
1!
b1 8
b0 9
b0 7
1)
#580000
0)
#585000
b0 &
b0 0
0!
b10101100000000000000000000000 $
b10101100000000000000000000000 /
b10 8
b1001000110100010101100000000000000000000000 7
b11000 <
1)
#590000
0)
#595000
b10 &
b10 0
1"
b11 8
b100 9
b100000 =
1)
#600000
0)
#605000
b0 8
b1111 #
b1111 .
b1111 6
1)
#610000
0)
#615000
0"
b0 $
b0 /
b1 &
b1 0
1!
b1 8
b0 9
b0 7
1)
#620000
0)
#625000
b0 &
b0 0
0!
b10101100000000000000000000000 $
b10101100000000000000000000000 /
b10 8
b1001000110100010101100000000000000000000000 7
b11000 <
b10 (
b10 ,
b1 '
b1 +
1)
#630000
0)
#635000
b10 &
b10 0
1"
b11 8
b100 9
b100000 =
1)
#640000
0)
#645000
b0 8
b10000 #
b10000 .
b10000 6
1)
#650000
0)
#655000
0"
b0 $
b0 /
b1 &
b1 0
1!
b1 8
b0 9
b1 :
b10 ;
b0 7
1)
#660000
0)
#665000
b10 $
b10 /
b10 8
b10 7
b11000 <
1)
#670000
0)
#675000
b11 &
b11 0
1"
b11 8
b1 %
b1 -
b1 5
b1 9
b100000 =
1)
#680000
0)
#685000
b0 8
b10001 #
b10001 .
b10001 6
1)
#690000
0)
#695000
b1 &
b1 0
0"
b0 $
b0 /
b1 8
b0 9
b0 7
1)
#700000
0)
#705000
b10 $
b10 /
b10 8
b10 7
b11000 <
1)
#710000
0)
#715000
b11 &
b11 0
1"
b11 8
b1 9
b100000 =
1)
#720000
0)
#725000
b0 8
b10010 #
b10010 .
b10010 6
1)
#730000
0)
#735000
b1 &
b1 0
0"
b0 $
b0 /
b1 8
b0 9
b0 7
1)
#740000
0)
#745000
b10 $
b10 /
b10 8
b10 7
b11000 <
1)
#750000
0)
#755000
b11 &
b11 0
1"
b11 8
b1 9
b100000 =
1)
#760000
0)
#765000
b0 8
b10011 #
b10011 .
b10011 6
1)
#770000
0)
#775000
b1 &
b1 0
0"
b0 $
b0 /
b1 8
b0 9
b0 7
1)
#780000
0)
#785000
b10 $
b10 /
b10 8
b10 7
b11000 <
1)
#790000
0)
#795000
b11 &
b11 0
1"
b11 8
b1 9
b100000 =
1)
#800000
0)
#805000
b0 8
b10100 #
b10100 .
b10100 6
1)
#810000
0)
#815000
b1 &
b1 0
0"
b0 $
b0 /
b1 8
b0 9
b0 7
1)
#820000
0)
#825000
b10 $
b10 /
b10 8
b10 7
b11000 <
1)
#830000
0)
#835000
b11 &
b11 0
1"
b11 8
b1 9
b100000 =
1)
#840000
0)
#845000
b0 8
b10101 #
b10101 .
b10101 6
1)
#850000
0)
#855000
b1 &
b1 0
0"
b0 $
b0 /
b1 8
b0 9
b0 7
1)
#860000
0)
#865000
b10 $
b10 /
b10 8
b10 7
b11000 <
1)
#870000
0)
#875000
b11 &
b11 0
1"
b11 8
b1 9
b100000 =
1)
#880000
0)
#885000
b0 8
b10110 #
b10110 .
b10110 6
1)
#890000
0)
#895000
b1 &
b1 0
0"
b0 $
b0 /
b1 8
b0 9
b0 7
1)
#900000
0)
#905000
b10 $
b10 /
b10 8
b10 7
b11000 <
1)
#910000
0)
#915000
b11 &
b11 0
1"
b11 8
b1 9
b100000 =
1)
#920000
0)
#925000
b0 8
b10111 #
b10111 .
b10111 6
1)
#930000
0)
#935000
b1 &
b1 0
0"
b0 $
b0 /
b1 8
b0 9
b0 7
1)
#940000
0)
#945000
b10 $
b10 /
b10 8
b10 7
b11000 <
1)
#950000
0)
#955000
b11 &
b11 0
1"
b11 8
b1 9
b100000 =
1)
#960000
0)
#965000
b0 8
b11000 #
b11000 .
b11000 6
1)
#970000
0)
#975000
b1 &
b1 0
0"
b0 $
b0 /
b1 8
b0 9
b0 7
1)
#980000
0)
#985000
b10 $
b10 /
b10 8
b10 7
b11000 <
1)
#990000
0)
#995000
b11 &
b11 0
1"
b11 8
b1 9
b100000 =
1)
#1000000
0)
#1005000
b0 8
b11001 #
b11001 .
b11001 6
1)
#1010000
0)
#1015000
b1 &
b1 0
0"
b0 $
b0 /
b1 8
b0 9
b0 7
1)
#1020000
0)
#1025000
b10 $
b10 /
b10 8
b10 7
b11000 <
1)
#1030000
0)
#1035000
b11 &
b11 0
1"
b11 8
b1 9
b100000 =
1)
#1040000
0)
#1045000
b0 8
b11010 #
b11010 .
b11010 6
1)
#1050000
0)
#1055000
b1 &
b1 0
0"
b0 $
b0 /
b1 8
b0 9
b0 7
1)
#1060000
0)
#1065000
b10 $
b10 /
b10 8
b10 7
b11000 <
1)
#1070000
0)
#1075000
b11 &
b11 0
1"
b11 8
b1 9
b100000 =
1)
#1080000
0)
#1085000
b0 8
b11011 #
b11011 .
b11011 6
1)
#1090000
0)
#1095000
b1 &
b1 0
0"
b0 $
b0 /
b1 8
b0 9
b0 7
1)
#1100000
0)
#1105000
b10 $
b10 /
b10 8
b10 7
b11000 <
1)
#1110000
0)
#1115000
b11 &
b11 0
1"
b11 8
b1 9
b100000 =
1)
#1120000
0)
#1125000
b0 8
b11100 #
b11100 .
b11100 6
1)
#1130000
0)
#1135000
b1 &
b1 0
0"
b0 $
b0 /
b1 8
b0 9
b0 7
1)
#1140000
0)
#1145000
b10 $
b10 /
b10 8
b10 7
b11000 <
1)
#1150000
0)
#1155000
b11 &
b11 0
1"
b11 8
b1 9
b100000 =
1)
#1160000
0)
#1165000
b0 8
b11101 #
b11101 .
b11101 6
1)
#1170000
0)
#1175000
b1 &
b1 0
0"
b0 $
b0 /
b1 8
b0 9
b0 7
1)
#1180000
0)
#1185000
b10 $
b10 /
b10 8
b10 7
b11000 <
1)
#1190000
0)
#1195000
b11 &
b11 0
1"
b11 8
b1 9
b100000 =
1)
#1200000
0)
#1205000
b0 8
b11110 #
b11110 .
b11110 6
1)
#1210000
0)
#1215000
b1 &
b1 0
0"
b0 $
b0 /
b1 8
b0 9
b0 7
1)
#1220000
0)
#1225000
b10 $
b10 /
b10 8
b10 7
b11000 <
1)
#1230000
0)
#1235000
b11 &
b11 0
1"
b11 8
b1 9
b100000 =
b100 (
b100 ,
b11 '
b11 +
1)
#1240000
0)
#1245000
b0 8
b11111 #
b11111 .
b11111 6
1)
#1250000
0)
#1255000
b1 &
b1 0
0"
b0 $
b0 /
b1 8
b0 9
b11 :
b100 ;
b0 7
1)
#1260000
0)
#1265000
b1100 $
b1100 /
b10 8
b1100 7
b11000 <
1)
#1270000
0)
#1275000
b11 &
b11 0
1"
b11 8
b10 %
b10 -
b10 5
b10 9
b100000 =
1)
#1280000
0)
#1285000
b0 8
b100000 #
b100000 .
b100000 6
1)
#1290000
0)
#1295000
b1 &
b1 0
0"
b0 $
b0 /
b1 8
b0 9
b0 7
1)
#1300000
0)
#1305000
b1100 $
b1100 /
b10 8
b1100 7
b11000 <
1)
#1310000
0)
#1315000
b11 &
b11 0
1"
b11 8
b10 9
b100000 =
1)
#1320000
0)
#1325000
b0 8
b100001 #
b100001 .
b100001 6
1)
#1330000
0)
#1335000
b1 &
b1 0
0"
b0 $
b0 /
b1 8
b0 9
b0 7
1)
#1340000
0)
#1345000
b1100 $
b1100 /
b10 8
b1100 7
b11000 <
1)
#1350000
0)
#1355000
b11 &
b11 0
1"
b11 8
b10 9
b100000 =
1)
#1360000
0)
#1365000
b0 8
b100010 #
b100010 .
b100010 6
1)
#1370000
0)
#1375000
b1 &
b1 0
0"
b0 $
b0 /
b1 8
b0 9
b0 7
1)
#1380000
0)
#1385000
b1100 $
b1100 /
b10 8
b1100 7
b11000 <
1)
#1390000
0)
#1395000
b11 &
b11 0
1"
b11 8
b10 9
b100000 =
1)
#1400000
0)
#1405000
b0 8
b100011 #
b100011 .
b100011 6
1)
#1410000
0)
#1415000
b1 &
b1 0
0"
b0 $
b0 /
b1 8
b0 9
b0 7
1)
#1420000
0)
#1425000
b1100 $
b1100 /
b10 8
b1100 7
b11000 <
1)
#1430000
0)
#1435000
b11 &
b11 0
1"
b11 8
b10 9
b100000 =
1)
#1440000
0)
#1445000
b0 8
b100100 #
b100100 .
b100100 6
1)
#1450000
0)
#1455000
b1 &
b1 0
0"
b0 $
b0 /
b1 8
b0 9
b0 7
1)
#1460000
0)
#1465000
b1100 $
b1100 /
b10 8
b1100 7
b11000 <
1)
#1470000
0)
#1475000
b11 &
b11 0
1"
b11 8
b10 9
b100000 =
1)
#1480000
0)
#1485000
b0 8
b100101 #
b100101 .
b100101 6
1)
#1490000
0)
#1495000
b1 &
b1 0
0"
b0 $
b0 /
b1 8
b0 9
b0 7
1)
#1500000
0)
#1505000
b1100 $
b1100 /
b10 8
b1100 7
b11000 <
1)
#1510000
0)
#1515000
b11 &
b11 0
1"
b11 8
b10 9
b100000 =
1)
#1520000
0)
#1525000
b0 8
b100110 #
b100110 .
b100110 6
1)
#1530000
0)
#1535000
b1 &
b1 0
0"
b0 $
b0 /
b1 8
b0 9
b0 7
1)
#1540000
0)
#1545000
b1100 $
b1100 /
b10 8
b1100 7
b11000 <
1)
#1550000
0)
#1555000
b11 &
b11 0
1"
b11 8
b10 9
b100000 =
1)
#1560000
0)
#1565000
b0 8
b100111 #
b100111 .
b100111 6
1)
#1570000
0)
#1575000
b1 &
b1 0
0"
b0 $
b0 /
b1 8
b0 9
b0 7
1)
#1580000
0)
#1585000
b1100 $
b1100 /
b10 8
b1100 7
b11000 <
1)
#1590000
0)
#1595000
b11 &
b11 0
1"
b11 8
b10 9
b100000 =
1)
#1600000
0)
#1605000
b0 8
b101000 #
b101000 .
b101000 6
1)
#1610000
0)
#1615000
b1 &
b1 0
0"
b0 $
b0 /
b1 8
b0 9
b0 7
1)
#1620000
0)
#1625000
b1100 $
b1100 /
b10 8
b1100 7
b11000 <
1)
#1630000
0)
#1635000
b11 &
b11 0
1"
b11 8
b10 9
b100000 =
1)
#1640000
0)
#1645000
b0 8
b101001 #
b101001 .
b101001 6
1)
#1650000
0)
#1655000
b1 &
b1 0
0"
b0 $
b0 /
b1 8
b0 9
b0 7
1)
#1660000
0)
#1665000
b1100 $
b1100 /
b10 8
b1100 7
b11000 <
1)
#1670000
0)
#1675000
b11 &
b11 0
1"
b11 8
b10 9
b100000 =
1)
#1680000
0)
#1685000
b0 8
b101010 #
b101010 .
b101010 6
1)
#1690000
0)
#1695000
b1 &
b1 0
0"
b0 $
b0 /
b1 8
b0 9
b0 7
1)
#1700000
0)
#1705000
b1100 $
b1100 /
b10 8
b1100 7
b11000 <
1)
#1710000
0)
#1715000
b11 &
b11 0
1"
b11 8
b10 9
b100000 =
1)
#1720000
0)
#1725000
b0 8
b101011 #
b101011 .
b101011 6
1)
#1730000
0)
#1735000
b1 &
b1 0
0"
b0 $
b0 /
b1 8
b0 9
b0 7
1)
#1740000
0)
#1745000
b1100 $
b1100 /
b10 8
b1100 7
b11000 <
1)
#1750000
0)
#1755000
b11 &
b11 0
1"
b11 8
b10 9
b100000 =
1)
#1760000
0)
#1765000
b0 8
b101100 #
b101100 .
b101100 6
1)
#1770000
0)
#1775000
b1 &
b1 0
0"
b0 $
b0 /
b1 8
b0 9
b0 7
1)
#1780000
0)
#1785000
b1100 $
b1100 /
b10 8
b1100 7
b11000 <
1)
#1790000
0)
#1795000
b11 &
b11 0
1"
b11 8
b10 9
b100000 =
1)
#1800000
0)
#1805000
b0 8
b101101 #
b101101 .
b101101 6
1)
#1810000
0)
#1815000
b1 &
b1 0
0"
b0 $
b0 /
b1 8
b0 9
b0 7
1)
#1820000
0)
#1825000
b1100 $
b1100 /
b10 8
b1100 7
b11000 <
1)
#1830000
0)
#1835000
b11 &
b11 0
1"
b11 8
b10 9
b100000 =
1)
